---
isTIL: false
date: "2023-05-14"
title: "íŒŒì´ì¬ List Comprehension"
categories: ["Tip", "Development"]
summary: "íŒŒì´ì¬ List Comprehensionì„ ì‚´í´ë´…ë‹ˆë‹¤."
thumbnail: "th.jpg"
---

### ë“¤ì–´ê°€ë©°,
ì–´ëŠë‚  ìš°ì—°íˆ íŒŒì´ì¬ ë¦¬ìŠ¤íŠ¸ ê´€ë ¨í•˜ì—¬ ê°„ë‹¨í•œ ì‹¤í—˜ì„ ìˆ˜í–‰í•˜ì˜€ìŠµë‹ˆë‹¤.

ë¦¬ìŠ¤íŠ¸ì— 0ë¶€í„° 1ì–µê¹Œì§€ì˜ ìˆ«ìë¥¼ ì¶”ê°€í•´ì•¼í•  ë•Œ,

append ì—°ì‚°ê³¼ list comprehensionì˜ ì‹¤í–‰ ì‹œê°„ì„ ë¹„êµí•˜ì˜€ëŠ”ë°ìš”,

ë¹ ë¥¸ ìˆœì„œëŒ€ë¡œ 3.68ì´ˆ, 8.02ì´ˆê°€ ë‚˜ì™”ìŠµë‹ˆë‹¤. (ì‹¤í–‰ ì‹œê°„ì€ í™˜ê²½ë§ˆë‹¤ ì°¨ì´ê°€ ìˆì„ ìˆ˜ ìˆìŠµë‹ˆë‹¤.)

ê·¸ë ‡ë‹¤ë©´ ê° ê¸°ë²•ì„ ë¹ ë¥¸ ìˆœì„œëŒ€ë¡œ ì˜¬ë°”ë¥´ê²Œ ë‚˜ì—´í•œ ê²ƒì€ ë¬´ì—‡ì¼ê¹Œìš”?

```python
import time

start_a_time = time.time()
a = []
b = []

MAX = 100000000  # 1ì–µ

# (a) append
for i in range(MAX):
    a.append(i)

print(time.time() - start_a_time)

start_b_time = time.time()
# (b) list comprehension
b = [i for i in range(MAX)]

print(time.time() - start_b_time)
```

### Python List Comprehension

ìœ„ ì½”ë“œëŠ” **list-comprehension, append  ìˆœì„œë¡œ ë¹ ë¥´ê²Œ ë™ì‘**í•©ë‹ˆë‹¤.  
ê·¸ëŸ°ë° ì™œ ì´ëŸ° ì°¨ì´ê°€ ë°œìƒí•˜ëŠ” ê²ƒì¼ê¹Œìš”?  

[íŒŒì´ì¬ì—ì„œ List Comprehensionì´ ë” ë¹ ë¥¸ ì´ìœ ](https://whatisand.github.io/why-fast-list-comprehension-python/)ì— ê·¸ ì´ìœ ê°€ ìì„¸íˆ ì„¤ëª…ë˜ì–´ ìˆìŠµë‹ˆë‹¤.  

ìš”ì•½í•˜ìë©´, **ë‘ ë©”ì„œë“œì˜ êµ¬í˜„ ë°©ì‹ì— ì°¨ì´**ê°€ ìˆê¸° ë•Œë¬¸ì…ë‹ˆë‹¤.   

appendì˜ ê²½ìš° list comprenesionê³¼ ë‹¤ë¥´ê²Œ **ë‚´ë¶€ì ìœ¼ë¡œ CALL_METHODë¥¼ ìˆ˜í–‰**í•˜ëŠ”ë°, ì—¬ê¸°ì„œ **ì˜¤ë²„í—¤ë“œê°€ ë°œìƒ**í•´ì„œ ëŠë ¤ì§„ ê²ƒì´ë¼ í•©ë‹ˆë‹¤.

ì°¸ê³ ë¡œ ë‘ ì½”ë“œì˜ ë°”ì´ë„ˆë¦¬ ë‹¨ì€  ì•„ë˜ì™€ ê°™ìŠµë‹ˆë‹¤.  ì½”ë“œëŠ” ìœ„ ë¸”ë¡œê·¸ í¬ìŠ¤íŠ¸ë¥¼ ì°¸ê³ í•˜ì˜€ìŠµë‹ˆë‹¤.
```python
#append ì—°ì‚°
import dis


def use_append():
    result = []
    for i in range(10000):
        result.append(i)
    return result


dis.dis(use_append)


# ì¶œë ¥ê²°ê³¼
  5           0 BUILD_LIST               0
              2 STORE_FAST               0 (result)

  6           4 LOAD_GLOBAL              0 (range)
              6 LOAD_CONST               1 (10000)
              8 CALL_FUNCTION            1
             10 GET_ITER
        >>   12 FOR_ITER                14 (to 28)
             14 STORE_FAST               1 (i)

  7          16 LOAD_FAST                0 (result)
             18 LOAD_METHOD              1 (append)
             20 LOAD_FAST                1 (i)
             22 CALL_METHOD              1
             24 POP_TOP
             26 JUMP_ABSOLUTE           12

  8     >>   28 LOAD_FAST                0 (result)
             30 RETURN_VALUE
```

```python
#list comprehension ì—°ì‚°
def use_comprehension():
    return [i for i in range(10000)]


dis.dis(use_comprehension)

# ì¶œë ¥ê²°ê³¼
 12           0 LOAD_CONST               1 (<code object <listcomp> at 0x7fdf372a1ea0, file "test.py", line 12>)
              2 LOAD_CONST               2 ('use_comprehension.<locals>.<listcomp>')
              4 MAKE_FUNCTION            0
              6 LOAD_GLOBAL              0 (range)
              8 LOAD_CONST               3 (10000)
             10 CALL_FUNCTION            1
             12 GET_ITER
             14 CALL_FUNCTION            1
             16 RETURN_VALUE

Disassembly of <code object <listcomp> at 0x7fdf372a1ea0, file "test.py", line 12>:
 12           0 BUILD_LIST               0
              2 LOAD_FAST                0 (.0)
        >>    4 FOR_ITER                 8 (to 14)
              6 STORE_FAST               1 (i)
              8 LOAD_FAST                1 (i)
             10 LIST_APPEND              2
             12 JUMP_ABSOLUTE            4
        >>   14 RETURN_VALUE
```

ê°œë°œì„ í•˜ë‹¤ë³´ë©´ ê°™ì€ ê¸°ëŠ¥ì„ ìˆ˜í–‰í•˜ì§€ë§Œ, ì„±ëŠ¥ì—ëŠ” ì°¨ì´ê°€ ë‚˜ëŠ” ê²½ìš°ê°€ ë§ì´ ìˆìŠµë‹ˆë‹¤!  
ì´ëŸ¬í•œ ê²ƒë“¤ì— í•œë²ˆ ê´€ì‹¬ì„ ê°€ì ¸ë³´ì‹œëŠ” ê²ƒë„ ì¶”ì²œë“œë¦½ë‹ˆë‹¤ ğŸ‘
